secret_learn-0.3.2.dist-info/licenses/LICENSE
secretlearn/__init__.py
secretlearn/algorithm_classifier.py
secretlearn/federated_learning/__init__.py
secretlearn/federated_learning/anomaly_detection/__init__.py
secretlearn/federated_learning/anomaly_detection/isolation_forest.py
secretlearn/federated_learning/calibration/__init__.py
secretlearn/federated_learning/calibration/calibrated_classifier_cv.py
secretlearn/federated_learning/clustering/__init__.py
secretlearn/federated_learning/clustering/affinity_propagation.py
secretlearn/federated_learning/clustering/agglomerative_clustering.py
secretlearn/federated_learning/clustering/birch.py
secretlearn/federated_learning/clustering/bisecting_kmeans.py
secretlearn/federated_learning/clustering/dbscan.py
secretlearn/federated_learning/clustering/feature_agglomeration.py
secretlearn/federated_learning/clustering/hdbscan.py
secretlearn/federated_learning/clustering/kmeans.py
secretlearn/federated_learning/clustering/mean_shift.py
secretlearn/federated_learning/clustering/mini_batch_kmeans.py
secretlearn/federated_learning/clustering/optics.py
secretlearn/federated_learning/clustering/spectral_biclustering.py
secretlearn/federated_learning/clustering/spectral_clustering.py
secretlearn/federated_learning/clustering/spectral_coclustering.py
secretlearn/federated_learning/covariance/__init__.py
secretlearn/federated_learning/covariance/elliptic_envelope.py
secretlearn/federated_learning/covariance/empirical_covariance.py
secretlearn/federated_learning/covariance/graphical_lasso.py
secretlearn/federated_learning/covariance/graphical_lasso_cv.py
secretlearn/federated_learning/covariance/ledoit_wolf.py
secretlearn/federated_learning/covariance/min_cov_det.py
secretlearn/federated_learning/covariance/oas.py
secretlearn/federated_learning/covariance/shrunkcovariance.py
secretlearn/federated_learning/cross_decomposition/__init__.py
secretlearn/federated_learning/cross_decomposition/cca.py
secretlearn/federated_learning/cross_decomposition/plscanonical.py
secret_learn-0.3.2.dist-info/METADATA
secret_learn-0.3.2.dist-info/WHEEL
secret_learn-0.3.2.dist-info/top_level.txt
secret_learn-0.3.2.dist-info/RECORD
