Metadata-Version: 2.4
Name: secret-learn
Version: 0.3.2
Summary: Privacy-preserving machine learning with SecretFlow - 573 implementations (191 algorithms × 3 modes: federated_learning/secret_sharing/split_learning) with JAX acceleration
Author-email: Chen Xingqiang <joy6677@outlook.com>
Maintainer-email: Secret-Learn developers <joy6677@outlook.com>
License: BSD-3-Clause
Project-URL: homepage, https://github.com/chenxingqiang/Secret-Learn
Project-URL: source, https://github.com/chenxingqiang/Secret-Learn
Project-URL: download, https://pypi.org/project/Secret-Learn/#files
Project-URL: tracker, https://github.com/chenxingqiang/Secret-Learn/issues
Project-URL: documentation, https://github.com/chenxingqiang/Secret-Learn#readme
Project-URL: JAX-sklearn, https://github.com/chenxingqiang/jax-sklearn
Project-URL: SecretFlow, https://github.com/secretflow/secretflow
Classifier: License :: OSI Approved :: BSD License
Classifier: Intended Audience :: Science/Research
Classifier: Intended Audience :: Developers
Classifier: Programming Language :: Python
Classifier: Programming Language :: Python :: 3
Classifier: Programming Language :: Python :: 3.10
Classifier: Programming Language :: Python :: 3.11
Classifier: Programming Language :: Python :: Implementation :: CPython
Classifier: Topic :: Software Development
Classifier: Topic :: Scientific/Engineering
Classifier: Topic :: Scientific/Engineering :: Artificial Intelligence
Classifier: Topic :: Security :: Cryptography
Classifier: Development Status :: 5 - Production/Stable
Classifier: Operating System :: Microsoft :: Windows
Classifier: Operating System :: POSIX
Classifier: Operating System :: Unix
Classifier: Operating System :: MacOS
Requires-Python: <3.12,>=3.10
License-File: LICENSE
Requires-Dist: numpy<3.0,>=1.22.0
Requires-Dist: scipy>=1.8.0
Requires-Dist: joblib>=1.2.0
Requires-Dist: threadpoolctl>=3.1.0
Requires-Dist: jax>=0.4.20
Requires-Dist: jaxlib>=0.4.20
Requires-Dist: jax-sklearn>=0.1.5
Requires-Dist: secretflow>=1.0.0
Provides-Extra: all
Requires-Dist: jax-sklearn>=0.1.5; extra == "all"
Requires-Dist: secretflow>=1.0.0; extra == "all"
Provides-Extra: jax-sklearn
Requires-Dist: jax-sklearn>=0.1.5; extra == "jax-sklearn"
Provides-Extra: secretflow
Requires-Dist: secretflow>=1.0.0; extra == "secretflow"
Provides-Extra: jax-cpu
Requires-Dist: jax[cpu]>=0.4.20; extra == "jax-cpu"
Provides-Extra: jax-cuda12
Requires-Dist: jax[cuda12]>=0.4.20; extra == "jax-cuda12"
Provides-Extra: jax-tpu
Requires-Dist: jax[tpu]>=0.4.20; extra == "jax-tpu"
Provides-Extra: benchmark
Requires-Dist: matplotlib>=3.5.0; extra == "benchmark"
Requires-Dist: pandas>=1.4.0; extra == "benchmark"
Requires-Dist: memory_profiler>=0.57.0; extra == "benchmark"
Provides-Extra: examples
Requires-Dist: matplotlib>=3.5.0; extra == "examples"
Requires-Dist: scikit-image>=0.19.0; extra == "examples"
Requires-Dist: pandas>=1.4.0; extra == "examples"
Requires-Dist: seaborn>=0.9.0; extra == "examples"
Requires-Dist: pooch>=1.6.0; extra == "examples"
Requires-Dist: plotly>=5.14.0; extra == "examples"
Provides-Extra: tests
Requires-Dist: pytest>=7.1.2; extra == "tests"
Requires-Dist: pytest-cov>=2.9.0; extra == "tests"
Dynamic: license-file
